configurations/__init__.py
utilities/__init__.py
aquality_selenium_core-0.0.4.dist-info/LICENSE
aquality_selenium_core-0.0.4.dist-info/METADATA
aquality_selenium_core-0.0.4.dist-info/WHEEL
aquality_selenium_core-0.0.4.dist-info/top_level.txt
aquality_selenium_core-0.0.4.dist-info/RECORD
