Metadata-Version: 2.1
Name: aquality-selenium-core
Version: 0.0.4
Summary: Core functionality for python-based aquality selenium libraries
Home-page: https://github.com/aquality-automation/aquality-selenium-core-python/
Author: Aleksandr Hramovich, Nikita Verbitsky, Nikita Kuznetsov, Pavel Anihimovsky
License: Apache-2.0
Project-URL: Source, https://github.com/aquality-automation/aquality-selenium-core-python
Project-URL: Tracker, https://github.com/aquality-automation/aquality-selenium-core-python/issues
Keywords: test,automation,qa,selenium
Platform: unix
Platform: linux
Platform: osx
Platform: win32
Classifier: Development Status :: 2 - Pre-Alpha
Classifier: Intended Audience :: Developers
Classifier: License :: OSI Approved :: Apache Software License
Classifier: Operating System :: MacOS :: MacOS X
Classifier: Operating System :: Microsoft :: Windows
Classifier: Operating System :: POSIX
Classifier: Programming Language :: Python :: 3
Classifier: Programming Language :: Python :: 3 :: Only
Classifier: Programming Language :: Python :: 3.5
Classifier: Programming Language :: Python :: 3.6
Classifier: Programming Language :: Python :: 3.7
Classifier: Programming Language :: Python :: 3.8
Classifier: Programming Language :: Python :: 3.9
Classifier: Topic :: Software Development :: Libraries
Classifier: Topic :: Software Development :: Testing
Classifier: Topic :: Utilities
Requires-Python: >=3.5
Requires-Dist: jsonpath-ng (==1.5.1)
Requires-Dist: selenium (==3.141.0)
Provides-Extra: checkqa_mypy
Requires-Dist: mypy (==0.780) ; extra == 'checkqa_mypy'
Provides-Extra: testing
Requires-Dist: pytest (==5.4.3) ; extra == 'testing'
Requires-Dist: PyHamcrest (==2.0.2) ; extra == 'testing'
